[
  {
    "inputs": [],
    "name": "InsufficientBalance",
    "type": "error"
  },
  {
    "inputs": [],
    "name": "NotAuthorized",
    "type": "error"
  },
  {
    "anonymous": false,
    "inputs": [
      {
        "indexed": true,
        "internalType": "address",
        "name": "insurer",
        "type": "address"
      },
      {
        "indexed": true,
        "internalType": "address",
        "name": "lender",
        "type": "address"
      },
      {
        "indexed": false,
        "internalType": "uint256",
        "name": "amount",
        "type": "uint256"
      }
    ],
    "name": "InsurancePayout",
    "type": "event"
  },
  {
    "anonymous": false,
    "inputs": [
      {
        "indexed": true,
        "internalType": "address",
        "name": "insurer",
        "type": "address"
      },
      {
        "indexed": false,
        "internalType": "uint256",
        "name": "amount",
        "type": "uint256"
      }
    ],
    "name": "InsurerDeposited",
    "type": "event"
  },
  {
    "inputs": [],
    "name": "deposit",
    "outputs": [],
    "stateMutability": "payable",
    "type": "function"
  },
  {
    "inputs": [
      {
        "internalType": "address",
        "name": "insurer",
        "type": "address"
      }
    ],
    "name": "getInsurerBalance",
    "outputs": [
      {
        "internalType": "uint256",
        "name": "",
        "type": "uint256"
      }
    ],
    "stateMutability": "view",
    "type": "function"
  },
  {
    "inputs": [],
    "name": "loanEscrowContract",
    "outputs": [
      {
        "internalType": "address",
        "name": "",
        "type": "address"
      }
    ],
    "stateMutability": "view",
    "type": "function"
  },
  {
    "inputs": [
      {
        "internalType": "address",
        "name": "insurer",
        "type": "address"
      },
      {
        "internalType": "address",
        "name": "lender",
        "type": "address"
      },
      {
        "internalType": "uint256",
        "name": "amount",
        "type": "uint256"
      }
    ],
    "name": "payout",
    "outputs": [],
    "stateMutability": "nonpayable",
    "type": "function"
  },
  {
    "inputs": [
      {
        "internalType": "address",
        "name": "_loanEscrow",
        "type": "address"
      }
    ],
    "name": "setLoanEscrowContract",
    "outputs": [],
    "stateMutability": "nonpayable",
    "type": "function"
  }
]